ragchecker/__init__.py
ragchecker/cli.py
ragchecker/computation.py
ragchecker/container.py
ragchecker/evaluator.py
ragchecker/integrations/llama_index.py
ragchecker/metrics.py
ragchecker-0.1.9.dist-info/LICENSE
ragchecker-0.1.9.dist-info/METADATA
ragchecker-0.1.9.dist-info/NOTICE
ragchecker-0.1.9.dist-info/WHEEL
ragchecker-0.1.9.dist-info/entry_points.txt
ragchecker-0.1.9.dist-info/RECORD
