Metadata-Version: 2.1
Name: ragchecker
Version: 0.1.9
Summary: RAGChecker: A Fine-grained Framework For Diagnosing Retrieval-Augmented Generation (RAG) systems.
License: Apache-2.0
Author: Xiangkun Hu
Author-email: xiangkhu@amazon.com
Requires-Python: >=3.9,<4.0
Classifier: License :: OSI Approved :: Apache Software License
Classifier: Programming Language :: Python :: 3
Classifier: Programming Language :: Python :: 3.9
Classifier: Programming Language :: Python :: 3.10
Classifier: Programming Language :: Python :: 3.11
Classifier: Programming Language :: Python :: 3.12
Requires-Dist: dataclasses-json (>=0.6,<0.7)
Requires-Dist: loguru (>=0.7,<0.8)
Requires-Dist: refchecker (>=0.2,<0.3)
